{
  "steps": [
    {
      "id": "intro-cloud",
      "step": 1,
      "title": "Introduction to Cloud Computing",
      "links": [
        "https://youtu.be/M988_fsOSWo?si=Gz0Wj3QvV6J4H9_T",
        "https://youtu.be/EN4fPBX0XyE?si=L4Z-wV8zPzXm-G-Q"
      ],
      "resources": [
        "https://aws.amazon.com/what-is-cloud-computing/"
      ]
    },
    {
      "id": "devops-basics",
      "step": 2,
      "title": "DevOps Fundamentals",
      "links": [
        "https://youtu.be/0yWAtQ6wMlM?si=C8D2oG-N8D-K-XjS"
      ],
      "resources": []
    },
    {
      "id": "linux-devops",
      "step": 3,
      "title": "Linux for DevOps",
      "links": [
        "https://youtu.be/5S-m6_mC0tI?si=PzVv9-XzXzX-G-Q"
      ],
      "resources": []
    },
    {
      "id": "docker-basics",
      "step": 4,
      "title": "Docker for Beginners",
      "links": [
        "https://youtu.be/pTFZFxd4hOI?si=PzVv9-XzXzX-G-Q"
      ],
      "resources": []
    },
    {
      "id": "aws-intro",
      "step": 5,
      "title": "AWS Cloud Practitioner Basics",
      "links": [
        "https://youtu.be/3hLmDS179YE?si=PzVv9-XzXzX-G-Q"
      ],
      "resources": []
    }
  ]
}
